incant/__init__.py
incant/_codegen.py
incant/_compat.py
incant/py.typed
incant-25.1.0.dist-info/METADATA
incant-25.1.0.dist-info/WHEEL
incant-25.1.0.dist-info/licenses/LICENSE
incant-25.1.0.dist-info/RECORD
