Metadata-Version: 2.4
Name: incant
Version: 25.1.0
Summary: Magical function composition
Project-URL: Home, https://github.com/Tinche/incant
Author-email: Tin Tvrtkovic <tinchester@gmail.com>
License: Apache License
License-File: LICENSE
Classifier: License :: OSI Approved :: Apache Software License
Classifier: Programming Language :: Python :: 3.9
Classifier: Programming Language :: Python :: 3.10
Classifier: Programming Language :: Python :: 3.11
Classifier: Programming Language :: Python :: 3.12
Classifier: Programming Language :: Python :: 3.13
Classifier: Programming Language :: Python :: 3.14
Classifier: Programming Language :: Python :: Implementation :: CPython
Classifier: Programming Language :: Python :: Implementation :: PyPy
Classifier: Typing :: Typed
Requires-Python: >=3.9
Requires-Dist: attrs>=20.1.0
